pipewelder/__init__.py
pipewelder/cli.py
pipewelder/connection.py
pipewelder/core.py
pipewelder/metadata.py
pipewelder/translator.py
pipewelder/util.py
pipewelder-0.1.4.dist-info/DESCRIPTION.rst
pipewelder-0.1.4.dist-info/entry_points.txt
pipewelder-0.1.4.dist-info/METADATA
pipewelder-0.1.4.dist-info/metadata.json
pipewelder-0.1.4.dist-info/RECORD
pipewelder-0.1.4.dist-info/top_level.txt
pipewelder-0.1.4.dist-info/WHEEL
