Metadata-Version: 2.0
Name: pipewelder
Version: 0.1.4
Summary: Scheduled task execution on top of AWS Data Pipeline
Home-page: http://github.com/jklukas/pipewelder
Author: Jeff Klukas
Author-email: klukas@simple.com
License: UNKNOWN
Platform: UNKNOWN
Classifier: Development Status :: 4 - Beta
Classifier: Environment :: Console
Classifier: Intended Audience :: Developers
Classifier: License :: OSI Approved :: Apache Software License
Classifier: Natural Language :: English
Classifier: Operating System :: OS Independent
Classifier: Programming Language :: Python :: 2.6
Classifier: Programming Language :: Python :: 2.7
Classifier: Programming Language :: Python :: 3.3
Classifier: Programming Language :: Python :: 3.4
Classifier: Topic :: Software Development :: Libraries :: Python Modules
Requires-Dist: boto
Requires-Dist: six
